simplelhs/__init__.py
simplelhs/lhs.py
simplelhs/normalisation.py
simplelhs-1.2.1.dist-info/METADATA
simplelhs-1.2.1.dist-info/WHEEL
simplelhs-1.2.1.dist-info/licenses/LICENSE
simplelhs-1.2.1.dist-info/RECORD
