Metadata-Version: 2.1
Name: simplelhs
Version: 1.2.1
Summary: Simple implementation of Latin Hypercube Sampling.
Project-URL: Homepage, https://github.com/mikediessner/simplelhs
Author-email: Mike Diessner <mikediessner@gmail.com>
License: MIT License
Keywords: Latin Hypercube Sampling,Python,Space filling design
Classifier: Development Status :: 4 - Beta
Classifier: Intended Audience :: Science/Research
Classifier: License :: OSI Approved :: MIT License
Classifier: Operating System :: OS Independent
Classifier: Programming Language :: Python :: 3
Requires-Python: >=3.7
Requires-Dist: numpy
Requires-Dist: scipy
